bitfeeds/__init__.py
bitfeeds/bitfeeds.py
bitfeeds/exchange.py
bitfeeds/instrument.py
bitfeeds/market.py
bitfeeds/subscription.py
bitfeeds/util.py
bitfeeds/broker/__init__.py
bitfeeds/broker/binance.py
bitfeeds/broker/bitfinex.py
bitfeeds/broker/bitmex.py
bitfeeds/broker/bitstamp.py
bitfeeds/broker/bittrex.py
bitfeeds/broker/btcc.py
bitfeeds/broker/cryptopia.py
bitfeeds/broker/gatecoin.py
bitfeeds/broker/gdax.py
bitfeeds/broker/huobi.py
bitfeeds/broker/kraken.py
bitfeeds/broker/liqui.py
bitfeeds/broker/luno.py
bitfeeds/broker/okcex.py
bitfeeds/broker/poloniex.py
bitfeeds/broker/quoine.py
bitfeeds/broker/restful_template.py
bitfeeds/broker/websocket_template.py
bitfeeds/broker/yunbi.py
bitfeeds-0.1.2.dist-info/DESCRIPTION.rst
bitfeeds-0.1.2.dist-info/METADATA
bitfeeds-0.1.2.dist-info/RECORD
bitfeeds-0.1.2.dist-info/WHEEL
bitfeeds-0.1.2.dist-info/entry_points.txt
bitfeeds-0.1.2.dist-info/metadata.json
bitfeeds-0.1.2.dist-info/top_level.txt
