Metadata-Version: 2.0
Name: bitfeeds
Version: 0.1.2
Summary: Crypto Currency Cxchange Market data feeder.
Home-page: https://github.com/bopo/bitfeeds/
Author: Bopo Wang
Author-email: ibopo@126.com
License: LICENSE.txt
Platform: UNKNOWN
Classifier: Development Status :: 2 - Pre-Alpha
Classifier: Intended Audience :: Developers
Classifier: License :: OSI Approved :: MIT License
Classifier: Natural Language :: English
Classifier: Programming Language :: Python :: 3
Classifier: Programming Language :: Python :: 3.3
Classifier: Programming Language :: Python :: 3.4
Classifier: Programming Language :: Python :: 3.5
Classifier: Programming Language :: Python :: 3.6
Requires-Dist: websocket-client
Requires-Dist: qpython
Requires-Dist: pymysql
Requires-Dist: numpy
Requires-Dist: pyzmq
